superbdataklient/__init__.py
superbdataklient/_internal_utils.py
superbdataklient/_logger_config.py
superbdataklient/api.py
superbdataklient/config.py
superb_data_klient-1.5.0.dist-info/LICENSE
superb_data_klient-1.5.0.dist-info/METADATA
superb_data_klient-1.5.0.dist-info/WHEEL
superb_data_klient-1.5.0.dist-info/top_level.txt
superb_data_klient-1.5.0.dist-info/RECORD
