Metadata-Version: 2.1
Name: superb-data-klient
Version: 1.5.0
Summary: A Python API wrapping services of the Superb Data Kraken (SDK)
Author-email: "Team SDK | e:fs TechHub GmbH" <sdk@efs-techhub.com>
Maintainer: Team SDK
Maintainer-email: sdk@efs-techhub.com
License: Apache-2.0
Keywords: sdk,superb data kraken,superbdataklient,super data klient,superb data klient,superb-data-klient,superb,data,klient
Classifier: Programming Language :: Python :: 3
Classifier: License :: OSI Approved :: Apache Software License
Classifier: Operating System :: OS Independent
Classifier: Development Status :: 3 - Alpha
Classifier: Intended Audience :: Developers
Requires-Python: >=3.7
License-File: LICENSE
Requires-Dist: requests >=2.31.0
Requires-Dist: opensearch-py >=2.3.0
Requires-Dist: PyJWT >=2.8.0
Requires-Dist: azure-core >=1.29.0
Requires-Dist: azure-storage-blob >=12.17.0
Requires-Dist: msrest >=0.7.0
Requires-Dist: TerevintoSoftware.PkceClient >=0.1.0
